LICENSE
MANIFEST.in
README.md
README.rst
pyproject.toml
sphinx_pdj_theme/__init__.py
sphinx_pdj_theme/breadcrumbs.html
sphinx_pdj_theme/footer.html
sphinx_pdj_theme/layout.html
sphinx_pdj_theme/searchbox.html
sphinx_pdj_theme/sidebar.html
sphinx_pdj_theme/theme.toml
sphinx_pdj_theme.egg-info/PKG-INFO
sphinx_pdj_theme.egg-info/SOURCES.txt
sphinx_pdj_theme.egg-info/dependency_links.txt
sphinx_pdj_theme.egg-info/entry_points.txt
sphinx_pdj_theme.egg-info/top_level.txt
sphinx_pdj_theme/__pycache__/__init__.cpython-312.pyc
sphinx_pdj_theme/__pycache__/__init__.cpython-313.pyc
sphinx_pdj_theme/locale/pt/LC_MESSAGES/sphinx.mo
sphinx_pdj_theme/locale/pt/LC_MESSAGES/sphinx.po
sphinx_pdj_theme/static/css/badge_only.css
sphinx_pdj_theme/static/css/darker.css
sphinx_pdj_theme/static/css/img.css
sphinx_pdj_theme/static/css/pdj.css
sphinx_pdj_theme/static/css/theme.css
sphinx_pdj_theme/static/fonts/fontawesome-webfont.eot
sphinx_pdj_theme/static/fonts/fontawesome-webfont.svg
sphinx_pdj_theme/static/fonts/fontawesome-webfont.ttf
sphinx_pdj_theme/static/fonts/fontawesome-webfont.woff
sphinx_pdj_theme/static/img/moon.svg
sphinx_pdj_theme/static/img/porao-branco.png
sphinx_pdj_theme/static/img/sun.svg
sphinx_pdj_theme/static/js/dark-mode-toggle.js
sphinx_pdj_theme/static/js/pdj.js
sphinx_pdj_theme/static/js/theme.js