Metadata-Version: 2.4
Name: sphinx-pdj-theme
Version: 0.7.0
Summary: A cool theme for sphinx documentation
Author: Juca Crispim
Project-URL: Homepage, https://github.com/jucacrispim/sphinx_pdj_theme/
Classifier: Programming Language :: Python :: 3
Classifier: License :: OSI Approved :: MIT License
Classifier: Operating System :: OS Independent
Classifier: Topic :: Software Development :: Libraries :: Python Modules
License-File: LICENSE
Dynamic: license-file
